grainsize/__init__.py
grainsize/clustering.py
grainsize/core.py
grainsize/mpaleo.py
grainsize-0.2.4.dist-info/METADATA
grainsize-0.2.4.dist-info/WHEEL
grainsize-0.2.4.dist-info/top_level.txt
grainsize-0.2.4.dist-info/RECORD
