Metadata-Version: 2.4
Name: grainsize
Version: 0.2.4
Summary: Sedimentological data‐analysis tools (grain‐size, XRF, forams, bryozoans)
Home-page: https://github.com/jvseds/SedLab
Author: Jarden Aaltonen
License: MIT
Classifier: Programming Language :: Python :: 3
Classifier: License :: OSI Approved :: MIT License
Classifier: Operating System :: OS Independent
Requires-Python: >=3.8
Requires-Dist: pandas>=2.0
Requires-Dist: numpy>=1.18
Requires-Dist: matplotlib>=3.0
Requires-Dist: scipy>=1.4
Requires-Dist: seaborn>=0.10
Dynamic: author
Dynamic: classifier
Dynamic: description
Dynamic: description-content-type
Dynamic: home-page
Dynamic: license
Dynamic: requires-dist
Dynamic: requires-python
Dynamic: summary
